sysbench_loader/__init__.py
sysbench_loader/_modidx.py
sysbench_loader/broad.py
sysbench_loader/core.py
sysbench_loader/industrial_robot.py
sysbench_loader/quad_pelican.py
sysbench_loader/quad_pi.py
sysbench_loader/ship.py
sysbench_loader/workshop.py
sysbench_loader-0.0.7.dist-info/LICENSE
sysbench_loader-0.0.7.dist-info/METADATA
sysbench_loader-0.0.7.dist-info/WHEEL
sysbench_loader-0.0.7.dist-info/entry_points.txt
sysbench_loader-0.0.7.dist-info/top_level.txt
sysbench_loader-0.0.7.dist-info/RECORD
